prsample/__init__.py
prsample/examples.py
prsample/prsample.py
prsample/version.py
prsample-0.0.5.dist-info/LICENSE
prsample-0.0.5.dist-info/METADATA
prsample-0.0.5.dist-info/WHEEL
prsample-0.0.5.dist-info/top_level.txt
prsample-0.0.5.dist-info/RECORD
